[
  {
    "model": "grms.qastatus",
    "pk": 1,
    "fields": {
      "status": "Draft"
    }
  },
  {
    "model": "grms.qastatus",
    "pk": 2,
    "fields": {
      "status": "In Review"
    }
  },
  {
    "model": "grms.qastatus",
    "pk": 3,
    "fields": {
      "status": "Approved"
    }
  },
  {
    "model": "grms.distresstype",
    "pk": 1,
    "fields": {
      "distress_code": "side_drain_silt",
      "distress_name": "Side Drain - Silt",
      "category": "road",
      "notes": ""
    }
  },
  {
    "model": "grms.distresstype",
    "pk": 2,
    "fields": {
      "distress_code": "side_drain_scour",
      "distress_name": "Side Drain - Scour",
      "category": "road",
      "notes": ""
    }
  },
  {
    "model": "grms.activitylookup",
    "pk": "121",
    "fields": {
      "activity_code": "121",
      "activity_name": "Drain Cleaning (culvert)",
      "default_unit": "m3",
      "is_resource_based": false,
      "notes": ""
    }
  },
  {
    "model": "grms.activitylookup",
    "pk": "122",
    "fields": {
      "activity_code": "122",
      "activity_name": "Ditch Cleaning (lined)",
      "default_unit": "m3",
      "is_resource_based": false,
      "notes": ""
    }
  },
  {
    "model": "grms.activitylookup",
    "pk": "230",
    "fields": {
      "activity_code": "230",
      "activity_name": "Ditch Cleaning (unlined)",
      "default_unit": "m3",
      "is_resource_based": false,
      "notes": ""
    }
  },
  {
    "model": "grms.activitylookup",
    "pk": "240",
    "fields": {
      "activity_code": "240",
      "activity_name": "Minor Carriageway Repair",
      "default_unit": "m",
      "is_resource_based": false,
      "notes": ""
    }
  },
  {
    "model": "grms.activitylookup",
    "pk": "241",
    "fields": {
      "activity_code": "241",
      "activity_name": "Major Carriageway Repair",
      "default_unit": "m3",
      "is_resource_based": true,
      "notes": ""
    }
  }
]